pandu/__init__.py
pandu/docs/Index.pdf
pandu/docs/docs_pandu.pdf
pandu/prac1/__init__.py
pandu/prac1/one.py
pandu/prac2/__init__.py
pandu/prac2/two.py
pandu/prac3/Ip_prac_3c.py
pandu/prac3/__init__.py
pandu/prac3/index.py
pandu/prac3/threeComplete.py
pandu/prac4/__init__.py
pandu/prac4/four.py
pandu/prac5/__init__.py
pandu/prac5/five.py
pandu/prac6/__init__.py
pandu/prac6/six.py
pandu/prac7/__init__.py
pandu/prac7/seven.py
pandu/tests/__init__.py
pandu/tests/test_prac1.py
pandu/tests/test_prac2.py
pandu-7.7.7.dist-info/licenses/LICENSE
pandu-7.7.7.dist-info/METADATA
pandu-7.7.7.dist-info/WHEEL
pandu-7.7.7.dist-info/top_level.txt
pandu-7.7.7.dist-info/RECORD
